[{"content":"总结 \n观看笔记 案例拆解 ","description":"OpenGL 编程入门教程","id":0,"section":"2_beginner","tags":["OpenGL"],"title":"OpenGL Graphics Programming","uri":"/zh/e1817400.html"},{"content":"官方文档\n\n","description":"Houdini 基础操作案例汇总","id":1,"section":"1_learning","tags":["知识汇总"],"title":"Houdini 基础操作案例汇总","uri":"/zh/56c557a6.html"},{"content":"  本网站基于 Hexo 静态网站生成工具构建，借助这个平台整理归纳 Houdini 的知识。\n本博客完全开源，欢迎大家参与贡献分享自己关于 Houdini 的经验总结 链接\n   文章建议以 markdown 投稿~\n网站特性里面展示了，网站支持的一些内容构建，可以点击右上角的编辑按钮在 Github 上查看文章的 Markdown 源码。\n ","description":"建站初衷","id":2,"section":"updates","tags":null,"title":"关于网站","uri":"/zh/updates/about.html"},{"content":"2021-02-13   Houdini in 5 Minutes - 案例分析 Lynda - Houdini Essential Training - 案例分析 Rohan Dalvi - Introduction to Houdini18 - 案例分析 Entagma Patreon- Adding Houdini to your Arsenal  - 观看笔记 \u0026amp; 案例分析   ","description":"教程完成进度","id":3,"section":"updates","tags":null,"title":"待办列表","uri":"/zh/updates/todo.html"}]